Giveme5W1H/__init__.py
Giveme5W1H/examples/__init__.py
Giveme5W1H/examples/extracting/__init__.py
Giveme5W1H/examples/extracting/index.html
Giveme5W1H/examples/extracting/parse_documents.py
Giveme5W1H/examples/extracting/parse_documents_with_enhancer.py
Giveme5W1H/examples/extracting/parse_single_from_code.py
Giveme5W1H/examples/extracting/server.py
Giveme5W1H/examples/startup/__init__.py
Giveme5W1H/examples/startup/environment.py
Giveme5W1H/examples/startup/environment_with_enhancer.py
Giveme5W1H/examples/startup/util.py
Giveme5W1H/extractor/__init__.py
Giveme5W1H/extractor/candidate.py
Giveme5W1H/extractor/configuration.py
Giveme5W1H/extractor/document.py
Giveme5W1H/extractor/extractor.py
Giveme5W1H/extractor/root.py
Giveme5W1H/extractor/combined_scoring/__init__.py
Giveme5W1H/extractor/combined_scoring/abs_combined_scoring.py
Giveme5W1H/extractor/combined_scoring/distance_of_candidate.py
Giveme5W1H/extractor/extractors/__init__.py
Giveme5W1H/extractor/extractors/abs_extractor.py
Giveme5W1H/extractor/extractors/action_extractor.py
Giveme5W1H/extractor/extractors/cause_extractor.py
Giveme5W1H/extractor/extractors/environment_extractor.py
Giveme5W1H/extractor/extractors/method_extractor.py
Giveme5W1H/extractor/preprocessors/__init__.py
Giveme5W1H/extractor/preprocessors/preprocessor_core_nlp.py
Giveme5W1H/extractor/resources/__init__.py
Giveme5W1H/extractor/tools/__init__.py
Giveme5W1H/extractor/tools/cache_manager.py
Giveme5W1H/extractor/tools/key_value_cache.py
Giveme5W1H/extractor/tools/mapper.py
Giveme5W1H/extractor/tools/timex.py
Giveme5W1H/extractor/tools/util.py
Giveme5W1H/extractor/tools/file/__init__.py
Giveme5W1H/extractor/tools/file/handler.py
Giveme5W1H/extractor/tools/file/reader.py
Giveme5W1H/extractor/tools/file/writer.py
giveme5w1h-1.0.5.dist-info/METADATA
giveme5w1h-1.0.5.dist-info/RECORD
giveme5w1h-1.0.5.dist-info/WHEEL
giveme5w1h-1.0.5.dist-info/entry_points.txt
giveme5w1h-1.0.5.dist-info/top_level.txt
