Metadata-Version: 2.1
Name: giveme5w1h
Version: 1.0.5
Summary: Extraction of the journalistic five W and one H questions (5W1H) from news articles.
Home-page: https://github.com/fhamborg/Giveme5W1H
Author: Felix Hamborg
Author-email: felix.hamborg@uni-konstanz.de
License: Apache License 2.0
Download-URL: https://github.com/fhamborg/Giveme5W1H
Keywords: question answering news event detection event extraction 5w fivew 5w1h fivewoneh question-answering qa reporters questions
Platform: UNKNOWN
Classifier: Development Status :: 4 - Beta
Classifier: Environment :: Console
Classifier: Intended Audience :: Developers
Classifier: Intended Audience :: Science/Research
Classifier: License :: OSI Approved :: Apache Software License
Classifier: Operating System :: MacOS
Classifier: Operating System :: Microsoft
Classifier: Operating System :: POSIX :: Linux
Classifier: Programming Language :: Python :: 3.6
Classifier: Topic :: Internet
Classifier: Topic :: Scientific/Engineering :: Information Analysis
Requires-Dist: unidecode
Requires-Dist: jinja2
Requires-Dist: requests
Requires-Dist: xmltodict
Requires-Dist: nltk (>=3.1.2)
Requires-Dist: flask (>=1.0.1)
Requires-Dist: editdistance (>=0.3.1)
Requires-Dist: geopy (>=1.11.0)
Requires-Dist: parsedatetime (>=2.2)
Requires-Dist: pycorenlp (>=0.3.0)
Requires-Dist: python-dateutil (>=2.6)
Requires-Dist: python-dateutil
Requires-Dist: lxml
Requires-Dist: numpy
Requires-Dist: pandas
Requires-Dist: parsedatetime
Requires-Dist: plotly
Requires-Dist: pycorenlp
Requires-Dist: spacy
Requires-Dist: Twisted
Requires-Dist: typing
Requires-Dist: Unidecode
